LICENSE
MANIFEST.in
README.md
requirements.txt
setup.py
lnr/__init__.py
lnr/lnr.py
lnr.egg-info/PKG-INFO
lnr.egg-info/SOURCES.txt
lnr.egg-info/dependency_links.txt
lnr.egg-info/not-zip-safe
lnr.egg-info/top_level.txt
tests/test_lnr.py