Metadata-Version: 2.1
Name: lnr
Version: 0.2.0
Summary: Various linear regression modules
Home-page: https://github.com/cristobal-sifon/lnr
Author: Cristobal Sifon
Author-email: sifon@astro.princeton.edu
License: UNKNOWN
Platform: UNKNOWN
License-File: LICENSE
